jgf/__init__.py
jgf/conmat.py
jgf/core.py
jgf/igraph.py
jgf/networkx.py
jgf-0.2.1.dist-info/LICENSE
jgf-0.2.1.dist-info/METADATA
jgf-0.2.1.dist-info/WHEEL
jgf-0.2.1.dist-info/top_level.txt
jgf-0.2.1.dist-info/RECORD
