Metadata-Version: 2.1
Name: jgf
Version: 0.2.1
Summary: Python library to load JGF files
Home-page: https://github.com/filipinascimento/jgf
Author: Filipi N. Silva
Author-email: filipi@iu.edu
License: UNKNOWN
Platform: UNKNOWN
Classifier: Programming Language :: Python :: 3
Classifier: License :: OSI Approved :: MIT License
Classifier: Operating System :: OS Independent
Requires-Python: >=3.0
